__init__.py
config.py
framework.py
inference.py
setup.cfg
setup.py
FCMADRL.egg-info/PKG-INFO
FCMADRL.egg-info/SOURCES.txt
FCMADRL.egg-info/dependency_links.txt
FCMADRL.egg-info/top_level.txt
ddpg/__init__.py
ddpg/actor_net.py
ddpg/actor_net_bn.py
ddpg/critic_net.py
ddpg/critic_net_bn.py
ddpg/ddpg.py
ddpg/main.py
ddpg/ou_noise.py
ddpg/result_plot.py
ddpg/tensorflow_grad_inverter.py
ddpg/tensorflow_session.py
dqn/__init__.py
dqn/dqn.py
framework/config.py
framework/framework.py
inference/inference.py