Metadata-Version: 1.0
Name: FCMADRL
Version: 0.9.dev0
Summary: Fully Cooperative Multi-Agent Deep Reinforcement Learning
Home-page: https://github.com/Nikunj-Gupta/FCMADRL
Author: Nikunj Gupta
Author-email: Nikunj.Gupta@iiitb.org
License: MIT License
Platform: UNKNOWN
